orderbot/__init__.py
orderbot/db_classes.py
orderbot/order.py
orderbot/order_parser.py
orderbot/orderbot.py
orderbot/util.py
Matrix_OrderBot-0.1.1.dist-info/entry_points.txt
Matrix_OrderBot-0.1.1.dist-info/WHEEL
Matrix_OrderBot-0.1.1.dist-info/METADATA
Matrix_OrderBot-0.1.1.dist-info/RECORD
