Metadata-Version: 2.1
Name: Matrix-OrderBot
Version: 0.1.1
License: MIT
Author-email: Zayus13 <sven_loechte@protonmail.com>
Requires-Python: >=3.8
Requires-Dist: SQLAlchemy==1.4.37
Requires-Dist: matrix-nio==0.19.0
